{
  "questions": [
    {
      "id": 1,
      "correct": 1,
      "q": "Which function is used to get the length of a string?",
      "first": "len()",
      "second": "count()",
      "third": "size()",
      "fourth": "length()"
    },
    {
      "id": 2,
      "correct": 2,
      "q": "test buestion",
      "first": "best one",
      "second": "best two",
      "third": "best three",
      "fourth": "best four"
    },
    {
      "id": 3,
      "correct": 3,
      "q": "test wuestion",
      "first": "west one",
      "second": "west two",
      "third": "west three",
      "fourth": "west four"
    }
  ],
  "profile": {
    "name": "typicode"
  }
}
